vtofg/__init__.py
vtofg/_run.py
vtofg/_tools.py
vtofg/funcgen.py
vtofg/plotter.py
vtofg/waves.py
vtofg-1.1.1.dist-info/LICENSE
vtofg-1.1.1.dist-info/METADATA
vtofg-1.1.1.dist-info/WHEEL
vtofg-1.1.1.dist-info/top_level.txt
vtofg-1.1.1.dist-info/RECORD
