Metadata-Version: 2.1
Name: vtofg
Version: 1.1.1
Summary: Vibration Test Object Function Generator
Author: Zack Ravetz
License: BSD 3-Clause License
Project-URL: Homepage, https://gitlab.com/zravetz/vtofg
Classifier: License :: OSI Approved :: BSD License
Classifier: Programming Language :: Python
Classifier: Programming Language :: Python :: 3
Requires-Python: >=3.7
License-File: LICENSE
Requires-Dist: numpy
Requires-Dist: pyaudio
Requires-Dist: matplotlib
